lib/__init__.py
lib/encrypt.py
wutongchain_cts/__init__.py
wutongchain_cts/api.py
wutongchain_cts/lib/__init__.py
wutongchain_cts/lib/encrypt.py
wutongchaincts/__init__.py
wutongchaincts/api.py
wutongchaincts/lib/__init__.py
wutongchaincts/lib/encrypt.py
wutongchain_cts-3.3.dist-info/LICENSE
wutongchain_cts-3.3.dist-info/METADATA
wutongchain_cts-3.3.dist-info/WHEEL
wutongchain_cts-3.3.dist-info/top_level.txt
wutongchain_cts-3.3.dist-info/RECORD
