Metadata-Version: 2.1
Name: wutongchain-cts
Version: 3.3
Summary: CTS是梧桐链（同济区块链）的轻量级独立服务，主要应用场景为存证，可以说是为存证领域而特制的，便于使用的API和服务，此为其Python SDK
Home-page: https://github.com/wally-yu/py-wutongchain-cts
Author: Wally Yu
License: MIT License
Platform: UNKNOWN
Requires-Dist: requests (>=2.10)
